qtl_power/__init__.py
qtl_power/extreme_pheno.py
qtl_power/gwas.py
qtl_power/rare_variants.py
tests/__init__.py
tests/test_extreme_pheno.py
tests/test_gwas.py
tests/test_rare_variants.py
qtl_power-0.5.0b0.dist-info/LICENSE.txt
qtl_power-0.5.0b0.dist-info/METADATA
qtl_power-0.5.0b0.dist-info/WHEEL
qtl_power-0.5.0b0.dist-info/top_level.txt
qtl_power-0.5.0b0.dist-info/RECORD
